lachin/__init__.py
lachin/lachin.py
lachin-0.1.0.dist-info/LICENSE
lachin-0.1.0.dist-info/METADATA
lachin-0.1.0.dist-info/WHEEL
lachin-0.1.0.dist-info/top_level.txt
lachin-0.1.0.dist-info/RECORD
