Metadata-Version: 2.1
Name: lachin
Version: 0.1.0
Summary: A Python Toolkit for Simulation of the UAVs.
Home-page: https://github.com/Haghrah/Lachin
Author: Amir Arslan Haghrah
Author-email: arslan.haghrah@gmail.com
License: MIT
Requires-Python: >=3.6
License-File: LICENSE
Requires-Dist: numpy
Requires-Dist: scipy
Requires-Dist: matplotlib
